lib_px_pkg_deps_channels/__init__.py
lib_px_pkg_deps_channels/file0.py
lib_px_pkg_deps_channels/folder1/__init__.py
lib_px_pkg_deps_channels/folder1/file1.py
lib_px_pkg_deps_channels/folder1/subfolder1/__init__.py
lib_px_pkg_deps_channels/folder1/subfolder1/file3.py
lib_px_pkg_deps_channels/folder2/__init__.py
lib_px_pkg_deps_channels/folder2/file2.py
multi_folder_pkg_deps_channels_insomniapx-0.0.1.dist-info/LICENSE
multi_folder_pkg_deps_channels_insomniapx-0.0.1.dist-info/METADATA
multi_folder_pkg_deps_channels_insomniapx-0.0.1.dist-info/WHEEL
multi_folder_pkg_deps_channels_insomniapx-0.0.1.dist-info/top_level.txt
multi_folder_pkg_deps_channels_insomniapx-0.0.1.dist-info/RECORD
