Metadata-Version: 2.1
Name: multi-folder-pkg-deps-channels-insomniapx
Version: 0.0.1
Summary: A multi-folder package (with dependencies from different conda channels) for insomniapx
Home-page: https://github.com/insomniapx-python-projects/py_package.git
Author: insomniapx
Author-email: insomniapx@gmail.com
License: UNKNOWN
Platform: UNKNOWN
Requires-Python: >=3.6
License-File: LICENSE
Requires-Dist: dependency-package-insomniapx (==0.0.2)
Requires-Dist: dependency-package-katiezhao (==0.0.2)
